OBP_devops_u1/__init__.py
OBP_devops_u1/cloudformation.py
OBP_devops_u1/codebuild.py
OBP_devops_u1/codedeploy_auto_rollback_monitor_enabled.py
OBP_devops_u1/codedeploy_ec2_minimum_healthy_hosts_configured.py
OBP_devops_u1/codedeploy_lambda_allatonce_traffic_shift_disabled.py
OBP_devops_u1/codepipeline.py
OBP_devops_u1/ecr.py
OBP_devops_u1/ecr_private_tag_immutability_enabled.py
OBP_devops_u1/ecs_container_insights_enabled.py
OBP_devops_u1/ecs_containers_non_privileged.py
OBP_devops_u1/ecs_containers_read_only_access.py
OBP_devops_u1/ecs_fargate_latest_platform_version.py
OBP_devops_u1/ecs_task_definition_memory_hard_limit.py
OBP_devops_u1/ecs_task_definition_nonroot_user.py
OBP_devops_u1/ecs_task_definition_pid_mode_check.py
OBP_devops_u1/ecs_task_definition_user_for_host_mode_check.py
OBP_devops_u1/eks.py
OBP_devops_u1/elastic_beanstalk.py
OBP_devops_u1/utils.py
OBP_devops_u1-0.2.3.dist-info/METADATA
OBP_devops_u1-0.2.3.dist-info/WHEEL
OBP_devops_u1-0.2.3.dist-info/top_level.txt
OBP_devops_u1-0.2.3.dist-info/RECORD
